speechkitty/__init__.py
speechkitty/directory.py
speechkitty/result_parser.py
speechkitty/transcriber.py
speechkitty-0.2.1.dist-info/LICENSE
speechkitty-0.2.1.dist-info/METADATA
speechkitty-0.2.1.dist-info/WHEEL
speechkitty-0.2.1.dist-info/top_level.txt
speechkitty-0.2.1.dist-info/RECORD
