Metadata-Version: 2.1
Name: speechkitty
Version: 0.2.1
Summary: A wrapper for two ASR services: Yandex SpeechKit and whisperX (based on OpenAI's Whisper) intended to asynchronously transcribe audio records.
Author-email: Aleksei Prishchepo <speechkitty@outlook.com>
License: Apache 2.0
Project-URL: Homepage, https://github.com/AlekseiPrishchepo/SpeechKitty
Project-URL: Source, https://github.com/AlekseiPrishchepo/SpeechKitty
Classifier: License :: OSI Approved :: Apache Software License
Classifier: Programming Language :: Python :: 3 :: Only
Classifier: Operating System :: OS Independent
Classifier: Development Status :: 2 - Pre-Alpha
Classifier: Topic :: Multimedia :: Sound/Audio :: Speech
Requires-Python: >=3.8
License-File: LICENSE
Requires-Dist: boto3
Requires-Dist: pandas
Requires-Dist: pydub
Requires-Dist: requests
Requires-Dist: python-dotenv
Requires-Dist: click
Provides-Extra: dev
Requires-Dist: pytest ; extra == 'dev'
Requires-Dist: moto ; extra == 'dev'
Requires-Dist: requests-mock ; extra == 'dev'
